{
  "title": "Découvrez votre Bureau numérique : l'Accueil",
  "addpadding": "#layout-content #contents",
  "iframecss": "padding-top:0px;padding-left:0px;",
  "stepper": {
    "title": "Explorez les fonctionnalités de l'Accueil du Bnum",
    "items": {
      "video": {
        "title": "Vidéo de présentation",
        "description": "Présentation du Bnum en vidéo",
        "bloc": {
          "title": "Voir la vidéo de présentation",
          "description": "<h2>Bienvenue sur votre Bureau Numérique !</h2><br/><p>Vous vous situez actuellement sur la page d'aide interractive du Bnum. Vous pouvez cliquer sur la vidéo pour découvrir un premier apperçu des fonctionnalités proposées par ce dernier.</p><p>Ci-dessous vous retrouvez le détail des fonctionnalitées de la page d'accueil que vous pourrez découvrir grâce à cette page d'aide. Cette page peut être fermée via le bouton \"Fermer\" ci-desous et réouverte à tout moment en passant par le bouton \"Assistance\".</p>",
          "video": "Capsule-1-Connexion.mp4",
          "img": "accueil.png"
        }
      },
      "navigation": {
        "title": "Barre de navigation",
        "description": "Barre de gauche pour naviguer entre les applications du Bnum",
        "highlight": "#layout-menu",
        "bloccss": "text-align: left; max-width: 35em; margin-left: 80px;text-align:justify",
        "iframecss": "padding-top:0px;padding-left:60px;",
        "button": "<span>En savoir plus</span><span class='icon-mel-arrow-right plus'></span>",
        "details": {
          "hintButtonLabel": "J'ai compris",
          "hints": [
            {
              "element": ".button-home",
              "hint": "L'accueil permet de revenir à la page principale du BNUM.",
              "hintPosition": "middle-right",
              "position": "right"
            },
            {
              "element": ".button-menu-last-frame",
              "hint": "Ce bouton permet de revenir sur la page précédement ouverte sans avoir à la recharger.",
              "position": "right",
              "hintPosition": "middle-right"
            },
            {
              "element": ".button-mail",
              "hint": "Mes courriels permet d'ouvrir votre messagerie web.",
              "position": "right",
              "hintPosition": "middle-right"
            },
            {
              "element": ".button-calendar",
              "hint": "le calendrier permet de gérer votre agenda et ceux sur lesquels vous avez des droits",
              "position": "right",
              "hintPosition": "middle-right"
            },
            {
              "element": ".button-rocket",
              "hint": "l'onglet Discussion permet un accès direct aux caneaux de discussion de Ariane",
              "position": "right",
              "hintPosition": "middle-right"
            },
            {
              "element": ".button-wsp",
              "hint": "'Mes espaces de travail' permet de gérer et de créer vos espaces de travails",
              "position": "right",
              "hintPosition": "middle-right"
            },
            {
              "element": ".button-stockage",
              "hint": "Le stockage permet de déposer/échanger des fichiers sur un espace de stockage distant",
              "position": "right",
              "hintPosition": "middle-right"
            },
            {
              "element": ".button-tasklist",
              "hint": "Le BNUM offre la possibilité de créer des listes de tâches à faire",
              "position": "right",
              "hintPosition": "middle-right"
            },
            {
              "element": ".button-contacts",
              "hint": "Permet d'accéder à l'ensemble de vos contacts et différents annuaires.",
              "position": "right",
              "hintPosition": "middle-right"
            },
            {
              "element": ".button-more-options",
              "hint": "Cet onglet regroupe d\"autre fonctionnalité comme le Kanban ou les sondages.",
              "hintPosition": "middle-right",
              "position": "right"
            },
            {
              "element": ".button-settings",
              "hint": "Cette page vous présente les options avec leur valeur par défaut.",
              "position": "right",
              "hintPosition": "middle-right"
            }
          ]
        },
        "bloc": {
          "title": "Barre de navigation",
          "description": "<br/><p>Il s'agit de la télécommande du Bureau Numérique. Elle est tout le temps accessible depuis n'importe quel écran du Bnum et permet de naviguer entre les applications.</p><p><strong>Bon à savoir :</strong> Avec le Bnum, plus besoin d'ouvrir plusieurs onglets, dés qu'une application est ouverte elle est gardée en mémoire et peut être réouverte instantanement à tout moment, le travail en cours ne sera pas perdu.</p>"
        }
      },
      "outils": {
        "title": "Barre d'outils",
        "description": "Barre du haut pour accéder rapidement à la création, à l'assistance et à la recherche",
        "highlight": "#layout header div.barup",
        "iframecss": "padding-top:60px;padding-left:0px;",
        "button": "<span>En savoir plus</span><span class='icon-mel-arrow-right plus'></span>",
        "details": {
          "nextLabel": "Suivant",
          "prevLabel": "Précédent",
          "doneLabel": "Fermer",
          "steps": [
            {
              "title": "Créer",
              "element": "#button-create",
              "intro": "Ce raccourci permet la création direct de contenu comme des mails ou encore des espaces de travail.",
              "popup": "Create",
              "button": "Montrez-moi !",
              "details": {
                "nextLabel": "Suivant",
                "prevLabel": "Précédent",
                "doneLabel": "Fermer",
                "steps": [
                  {
                    "title": "Espace de travail",
                    "intro": "Un espace de travail permet de créer un espace de travail directement dans cette interface",
                    "element": "#workspace button",
                    "position": "right",
                    "hintPosition": "top-right"
                  },
                  {
                    "title": "Email",
                    "intro": "Un email permet d'ouvrir l'interface de création d'un nouvel email",
                    "element": "#mail button",
                    "position": "right",
                    "hintPosition": "top-right"
                  },
                  {
                    "title": "Évènement",
                    "intro": "Un évènement permet de créer un évènement directement dans votre agenda",
                    "element": "#reu button",
                    "position": "right",
                    "hintPosition": "top-right"
                  },
                  {
                    "title": "Web-conférence",
                    "intro": "Ouvre la page de création d'une web-conférence",
                    "element": "#viso button",
                    "position": "right",
                    "hintPosition": "top-right"
                  },
                  {
                    "title": "Tâche",
                    "intro": "Le BNUM vous offre la possibilité de créer des listes de tâches à faire",
                    "element": "#tache button",
                    "position": "right",
                    "hintPosition": "top-right"
                  },
                  {
                    "title": "Document",
                    "intro": "Un document permet de créer directement un nouveau fichier (Texte, office, excel ...)",
                    "element": "#document button",
                    "position": "right",
                    "hintPosition": "top-right"
                  },
                  {
                    "title": "Bloc-note",
                    "intro": "Ouvre l'outil bloc note du BNUM",
                    "element": "#blocnote button",
                    "position": "right",
                    "hintPosition": "top-right"
                  },
                  {
                    "title": "Pégase",
                    "intro": "Ouvre la page de sondage de l'outil 'Pégase'",
                    "element": "#pega button",
                    "position": "right",
                    "hintPosition": "top-right"
                  }
                ]
              },
              "position": "bottom"
            },
            {
              "title": "Assistance",
              "element": "#button-help",
              "intro": "Ce raccourci ouvre une popup contenant toutes les demandes d'assistances (aides, propositions d'amélioration)",
              "position": "bottom",
              "popup": "Help",
              "button": "Montrez-moi",
              "details": {
                "nextLabel": "Suivant",
                "prevLabel": "Précédent",
                "doneLabel": "Fermer",
                "steps": [
                  {
                    "title": "Barre de recherche",
                    "element": "#help-search",
                    "intro": "Ce champ de recherche vous permet de rechercher votre besoin en quelques mots",
                    "position": "bottom"
                  },
                  {
                    "title": "Aide générale",
                    "element": ".helppage.general a",
                    "intro": "'Voir l'aide générale de Mél' permet d'ouvrir l'ancienne page d'aide de l'outil Mél",
                    "position": "bottom"
                  },
                  {
                    "title": "Aide page courante",
                    "element": ".helppage.current a",
                    "intro":  "'Voir l'aide de la page courante' permet de réafficher cette aide",
                    "position": "bottom"
                  },
                  {
                    "title": "Proposer une amélioration",
                    "element": ".helppage.suggestion a",
                    "intro": "Il est possible de proposer une idée d'évolution pour Mél (innovation, ergonomie, nouvelle fonctionnalité ...).Il ne s'agit pas de régler des problèmes d'utilisation ou de mauvais fonctionnement qui doivent être adresser à votre cellule informatique de proximité.",
                    "position": "bottom",
                    "tooltipClass": "big-width-intro"
                  },
                  {
                    "title": "Actualités",
                    "element": "#helpnews",
                    "intro":  "L'onglet 'Actualité' affiche toutes les dernières nouveautés liées au BNUM ",
                    "position": "bottom"
                  }
                ]
              }
            },
            {
              "title": "Mes raccourcis",
              "element": "#button-shortcut",
              "popup": "Shortcut",
              "intro": "Mes raccourcis permet d'afficher vos tâches et évènements du jour",
              "button": "Démonstration",
              "details": {
                "tooltipClass": "index-maj",
                "nextLabel": "Suivant",
                "prevLabel": "Précédent",
                "doneLabel": "Fermer",
                "steps": [
                  {
                    "title": "Mes tâches",
                    "element": ".shortcut-task",
                    "intro": "Contient la liste de toutes vos tâches à venir",
                    "position": "bottom"
                  },
                  {
                    "title": "Mes évènements",
                    "element": ".shortcut-task.shorcut-calendar",
                    "intro": "Permet de voir vos évènements du jour",
                    "position": "right"
                  }
                ]
              },
              "position": "bottom"
            },
            {
              "title": "Recherche",
              "element": ".search",
              "intro": "Vous permet de recherchez des mots clés présent dans vos emails, documents ou agendas",
              "position": "bottom"
            },
            {
              "title": "Mon compte",
              "element": "#user-up-popup",
              "popup": "User",
              "intro": "Menu déroulant regroupant certaines options pratiques (Rafraîchir la page, options d'avatar...)",
              "button": "Dérouler le menu",
              "details": {
                "nextLabel": "Suivant",
                "prevLabel": "Précédent",
                "doneLabel": "Fermer",
                "steps": [
                  {
                    "title": "Rafraîchir",
                    "element": ".refresh.refresh-current-thing",
                    "intro": "Permet d'actualiser la page en cours",
                    "position": "left"
                  },
                  {
                    "title": "Cacher",
                    "element": ".settings.toggleChatCommand ",
                    "intro": "Permet de cacher la bulle de discussion située en bas à droite de votre écran",
                    "position": "left"
                  },
                  {
                    "title": "Mes options",
                    "element": ".settings.my_account ",
                    "intro": "Ouvre les options du bureau numérique",
                    "position": "left"
                  },
                  {
                    "title": "Changer d'avatar",
                    "element": ".settings.avatar ",
                    "intro": "Ouvre les options pour changer votre avatar",
                    "position": "left"
                  },
                  {
                    "title": "Déconnexion",
                    "element": ".logout.logout-color ",
                    "intro": "Vous permet de vos déconnecter du bureau numérique",
                    "position": "left"
                  }
                ]
              },
              "position": "bottom"
            },
            {
              "title": "Changer de thème",
              "element": ".theme-mode-switch",
              "intro": "Permet de passer facilement du thème clair au thème sombre et vice versa",
              "position": "bottom"
            }
          ]
        },
        "bloc": {
          "title": "Barre d'outils",
          "description": "<p>Cette barre d'outils reste tout le temps accessible quelque soit la page du Bnum affichée.</p><p>Elle permet d'accéder rapidement aux fonctionnalités importantes du Bureau Numérique :</p><ul class='onboarding-list'><li>Créer des espaces de travail, des mails, des rendez-vous</li><li>Accéder à l'assistance</li><li>Les raccourcis vers l'affichage de \"Ma journée\"</li><li>La recherche globales dans les mails, contacts et rendez-vous</li><li>Le menu Bienvenue permettant de se déconnecter</li></ul>"
        }
      },
      "accueil-majournee": {
        "title": "Ma journée",
        "description": "Affichage des tâches et rendez-vous du jour",
        "highlight": "#layout-content #contents div.--col-dwp-1",
        "scrollto": true,
        "scrolltop": 250,
        "css": "background-color: #fff; border-radius: 5px; z-index: 1001; box-shadow: 1px 1px 10px 1px rgba(255, 255, 255, 0.7);",
        "bloccss": "margin-left: 45%;max-width:600px;text-align:start",
        "bloc": {
          "title": "Page d'accueil : Ma journée",
          "description": "<br/>\"Ma journée\" permet de visualiser les rendez-vous de la journée ainsi que les tâches en cours. Si un rendez-vous possède un lien de visioconférence, ce lien sera directement cliquable depuis ce menu."
        }
      },
      "accueil-informations": {
        "title": "Informations",
        "description": "Affichage des informations du service et du ministère",
        "highlight": "#layout-content #contents div.--col-dwp-2",
        "scrollto": true,
        "scrolltop": 250,
        "css": "background-color: #fff; border-radius: 5px; z-index: 1001; box-shadow: 1px 1px 10px 1px rgba(255, 255, 255, 0.7);",
        "bloccss": "margin-right: 65%;text-align:end",
        "bloc": {
          "title": "Page d'accueil : Informations",
          "description": "<br/>\"Informations\" permet de visualiser les informations importantes diffusées par votre service ainsi que celles diffusées par votre ministère"
        }
      },
      "accueil-espaces-de-travail": {
        "title": "Mes espaces de travail",
        "description": "Affichage des trois derniers espaces de travail",
        "highlight": "#layout-content #contents div.--col-dwp-3",
        "scrollto": true,
        "scrolltop": 660,
        "css": "background-color: #fff; border-radius: 5px; z-index: 1001; box-shadow: 1px 1px 10px 1px rgba(255, 255, 255, 0.7);",
        "bloccss": "margin-top: 10%;margin-right:auto;margin-left:auto;max-width:50%",
        "bloc": {
          "title": "Page d'accueil : Mes espaces de travail",
          "description": "<br/>\"Mes espaces de travail\" vous affiche les trois derniers espaces de travail accessibles directement depuis le Bnum. Vous pouvez visualiser les informations de ces espaces et les ouvrir directement depuis ce menu."
        }
      }
    }
  }
}